pdf_craft/__init__.py
pdf_craft/markdown.py
pdf_craft/template.py
pdf_craft/utils.py
pdf_craft/analyser/__init__.py
pdf_craft/analyser/asset_matcher.py
pdf_craft/analyser/chapter.py
pdf_craft/analyser/chunk_file.py
pdf_craft/analyser/citation.py
pdf_craft/analyser/common.py
pdf_craft/analyser/index.py
pdf_craft/analyser/main_text.py
pdf_craft/analyser/meta.py
pdf_craft/analyser/ocr_extractor.py
pdf_craft/analyser/page.py
pdf_craft/analyser/page_clipper.py
pdf_craft/analyser/position.py
pdf_craft/analyser/serial.py
pdf_craft/analyser/state_machine.py
pdf_craft/analyser/types.py
pdf_craft/analyser/utils.py
pdf_craft/analyser/window.py
pdf_craft/data/prompts/citation.jinja
pdf_craft/data/prompts/index.jinja
pdf_craft/data/prompts/main_text.jinja
pdf_craft/data/prompts/meta.jinja
pdf_craft/data/prompts/page.jinja
pdf_craft/data/prompts/position.jinja
pdf_craft/data/prompts/common/fix_ocr.jinja
pdf_craft/data/prompts/common/orc_blocks.jinja
pdf_craft/data/prompts/common/page_blocks.jinja
pdf_craft/data/prompts/common/quote.jinja
pdf_craft/data/prompts/common/xml_format.jinja
pdf_craft/data/templates/container.xml.jinja
pdf_craft/data/templates/content.opf.jinja
pdf_craft/data/templates/cover.xhtml.jinja
pdf_craft/data/templates/mimetype.jinja
pdf_craft/data/templates/part.xhtml.jinja
pdf_craft/data/templates/style.css.jinja
pdf_craft/data/templates/toc.ncx.jinja
pdf_craft/epub/__init__.py
pdf_craft/epub/context.py
pdf_craft/epub/gen_asset.py
pdf_craft/epub/gen_epub.py
pdf_craft/epub/gen_index.py
pdf_craft/epub/gen_part.py
pdf_craft/epub/i18n.py
pdf_craft/epub/template.py
pdf_craft/epub/types.py
pdf_craft/llm/__init__.py
pdf_craft/llm/error.py
pdf_craft/llm/escape.py
pdf_craft/llm/executor.py
pdf_craft/llm/increasable.py
pdf_craft/llm/node.py
pdf_craft/pdf/__init__.py
pdf_craft/pdf/document.py
pdf_craft/pdf/extractor.py
pdf_craft/pdf/section.py
pdf_craft/pdf/text_matcher.py
pdf_craft/pdf/types.py
pdf_craft/pdf/utils.py
tests/__init__.py
tests/test_framework.py
pdf_craft_cloud-0.1.3.dist-info/LICENSE
pdf_craft_cloud-0.1.3.dist-info/METADATA
pdf_craft_cloud-0.1.3.dist-info/WHEEL
pdf_craft_cloud-0.1.3.dist-info/top_level.txt
pdf_craft_cloud-0.1.3.dist-info/RECORD
