Metadata-Version: 2.1
Name: pdf-craft-cloud
Version: 0.1.3
Summary: PDF craft can convert PDF files into various other formats. This project will focus on processing PDF files of scanned books. The project has just started.
Home-page: https://github.com/oomol-lab/pdf-craft
Author: Tao Zeyu
Author-email: i@taozeyu.com
Classifier: Development Status :: 2 - Pre-Alpha
Classifier: Intended Audience :: Developers
Classifier: License :: OSI Approved :: GNU Affero General Public License v3
Classifier: Programming Language :: Python
Classifier: Programming Language :: Python :: 3.10
License-File: LICENSE
Requires-Dist: jinja2<4.0.0,>=3.1.5
Requires-Dist: pyMuPDF<2.0.0,>=1.25.3
Requires-Dist: alphabet-detector<1.0.0,>=0.0.7
Requires-Dist: shapely<3.0.0,>=2.0.6
Requires-Dist: latex2mathml<4.0.0,>=3.77.0
Requires-Dist: matplotlib<3.11.0,>=3.10.1
Requires-Dist: tiktoken<1.0.0,>=0.9.0
Requires-Dist: doc-page-extractor==0.2.0
Requires-Dist: resource-segmentation==0.0.1
Requires-Dist: langchain[openai]<0.4.0,>=0.3.21
